fastrtc_whisper_cpp/__init__.py
fastrtc_whisper_cpp/constants.py
fastrtc_whisper_cpp/utils.py
fastrtc_whisper_cpp/speech_to_text/__init__.py
fastrtc_whisper_cpp/speech_to_text/stt_.py
fastrtc_whisper_cpp/speech_to_text/test_file.wav
fastrtc_whisper_cpp-0.1.2.dist-info/METADATA
fastrtc_whisper_cpp-0.1.2.dist-info/WHEEL
fastrtc_whisper_cpp-0.1.2.dist-info/licenses/LICENSE
fastrtc_whisper_cpp-0.1.2.dist-info/RECORD
