Metadata-Version: 2.4
Name: fastrtc-whisper-cpp
Version: 0.1.2
Summary: Fast RTC Whisper CPP package
Project-URL: Homepage, https://github.com/mahimairaja/fastrtc-whisper-cpp
Project-URL: Bug Tracker, https://github.com/mahimairaja/fastrtc-whisper-cpp/issues
Author-email: Mahimai Raja <night-myriad.1y@icloud.com>
License-Expression: MIT
License-File: LICENSE
Requires-Python: >=3.10
Requires-Dist: click>=8.2.1
Requires-Dist: numpy>=2.0.2
Requires-Dist: pywhispercpp>=1.3.1
Provides-Extra: audio
Requires-Dist: librosa>=0.9.0; extra == 'audio'
Provides-Extra: dev
Requires-Dist: black; extra == 'dev'
Requires-Dist: isort; extra == 'dev'
Requires-Dist: pre-commit>=4.2.0; extra == 'dev'
Requires-Dist: pytest; extra == 'dev'
